{
    "Vittoria di Savoia": {
        "height": 1.73, "nsfw": "true",
        "shoe_size": 8, "country": "IT",
        "birthday": "December 28, 2003",
        "language": {
            "RU": { "title": "Виктория Савойская" },
            "UA": { "title": "Вітторія Савойська" },
            "BG": { "title": "Виктория Савойска" },
            "CZ": { "title": "Vittoria Savojská" },
            "FR": { "title": "Vittoria de Savoie" },
            "BE": { "title": "Vittoria de Savoie" },
            "ES": { "title": "Victoria de Saboya" },
            "MX": { "title": "Victoria de Saboya" }
        }
    },
    "Audrey Hepburn": {
        "height": 1.7, "weight": 47,
        "sizes": "76-51-86", "nsfw": "true",
        "shoe_size": 10.5, "country": "EU",
        "birthday": "May 4, 1929",
        "deathday": "January 20, 1993",
        "language": {
            "RU": { "title": "Одри Хепберн" }
        }
    },
    "Sydney Sweeney": {
        "height": 1.61, "weight": 56,
        "sizes": "91-63-91", "nsfw": "true",
        "shoe_size": 7.5, "country": "US",
        "birthday": "September 12, 1997",
        "language": {
            "RU": { "title": "Сидни Суини" }
        }
    },
    "Marilyn Monroe": {
        "height": 1.66, "weight": 54,
        "sizes": "91-56-91", "nsfw": "true",
        "shoe_size": 7, "country": "US",
        "birthday": "June 1, 1926",
        "deathday": "August 5, 1962",
        "language": {
            "RU": { "title": "Мэрилин Монро" }
        }
    },
    "Cara Delevingne": {
        "height": 1.73, "weight": 51,
        "sizes": "81-61-87", "nsfw": "true",
        "shoe_size": 8.5, "country": "GB",
        "birthday": "August 12, 1992",
        "language": {
            "RU": { "title": "Кара Делевинь" }
        }
    },
    "Victoria Justice": {
        "height": 1.66, "weight": 53,
        "sizes": "87-61-89", "nsfw": "true",
        "shoe_size": 7, "country": "US",
        "birthday": "February 19, 1993",
        "language": {
            "RU": { "title": "Виктория Джастис" }
        }
    },
    "Camila Cabello": {
        "height": 1.57, "weight": 50,
        "sizes": "87-64-90", "nsfw": "true",
        "shoe_size": 7, "country": "US",
        "birthday": "March 3, 1997",
        "language": {
            "RU": { "title": "Камила Кабельо" }
        }
    },
    "Olivia Culpo": {
        "height": 1.66, "weight": 52,
        "sizes": "81-64-89", "nsfw": "true",
        "shoe_size": 8, "country": "US",
        "birthday": "May 8, 1992",
        "language": {
            "RU": { "title": "Оливия Калпо" }
        }
    },
    "Barbara Palvin": {
        "height": 1.75, "weight": 58,
        "sizes": "85-59-89", "nsfw": "true",
        "shoe_size": 8, "country": "HU",
        "birthday": "October 8, 1993",
        "language": {
            "RU": { "title": "Барбара Палвин" }
        }
    },
    "Brigitte Bardot": {
        "height": 1.66, "weight": 57,
        "sizes": "89-63-89", "nsfw": "true",
        "shoe_size": 7.5, "country": "FR",
        "birthday": "September 28, 1934",
        "language": {
            "RU": { "title": "Брижит Бардо" }
        }
    },
    "007 ELEMENTS": {
        "country": "AT", "insignia": "007",
        "maison": "https://www.007.com",
        "memoir": "007 ELEMENTS is the new James Bond cinematic installation opening this winter built inside the summit of the Gaislachkogl Mountain in Sölden. The name 007 ELEMENTS reflects the visitor’s journey through a series of galleries, each distilling the craft of the signature elements that define a James Bond film. The installation will focus on Spectre, which was shot in Sölden, but will also feature other titles in the James Bond franchise. The collaboration between the project’s Creative Director Neal Callow (Art Director on Casino Royale, Quantum Of Solace, Skyfall and Spectre) and Optimist Inc. Head of Design Tino Schaedler and his team has resulted in an immersive, interactive, and educational experience that places visitors inside the world of 007 while revealing how that world is made. \"Our aim with 007 ELEMENTS is to tell the narrative of the Bond story in an emotional and engaging way”, said Callow. “We want to use this incredible location to place our guests into Bond’s environment, and bring the stories to life in a unique and unforgettable way.\" Located 3050 meters above sea level, the 1,300 square meter building has been constructed within the mountain and is arranged over two levels. Blending seamlessly with its surroundings, the impressive structure reveals itself through a tunnel and unfolds into two main areas offering spectacular views of the Tyrolean valleys. The bespoke new building to house the installation was designed and is currently being constructed by Obermoser Architects. Tyrolean architect Johann Obermoser and his team have been planning and realising award-winning commercial and residential buildings since 1983 including the spectacular ice Q restaurant on the summit of the Gaislachkogl and the Gaislachkogelbahn and Giggijochbahn cable car stations in Sölden. Combining state-of-the-art technology with stark contemporary architecture, 007 ELEMENTS creates a captivating experience with a dramatic cinematic soundscape set in nature’s awe-inspiring surroundings.",
        "language": {
            "RU": {
                "memoir": "007 ELEMENTS — это новая кинематографическая инсталляция Джеймса Бонда, которая откроется этой зимой и будет построена на вершине горы Гайслахкогль в Зельдене. Название 007 ELEMENTS отражает путешествие посетителя по ряду галерей, каждая из которых раскрывает мастерство фирменных элементов, определяющих фильм о Джеймсе Бонде. Инсталляция будет посвящена фильму «007: Спектр», который снимался в Зельдене, но также будет включать другие фильмы из франшизы о Джеймсе Бонде. Сотрудничество между креативным директором проекта Нилом Кэллоу (арт-директор фильмов «Казино Рояль», «Квант милосердия», «007: Координаты «Скайфолл»» и «007: Спектр») и руководителем отдела дизайна Optimist Inc. Тино Шедлером и его командой привело к созданию захватывающего, интерактивного и образовательного опыта, который помещает посетителей в мир 007, одновременно показывая, как устроен этот мир. «Наша цель с 007 ELEMENTS — рассказать историю Бонда эмоционально и увлекательно», — сказал Кэллоу. «Мы хотим использовать это невероятное место, чтобы поместить наших гостей в среду Бонда и воплотить истории в жизнь уникальным и незабываемым образом». Расположенное на высоте 3050 метров над уровнем моря, здание площадью 1300 квадратных метров было построено внутри горы и расположено на двух уровнях. Плавно сливаясь с окружающей средой, впечатляющее сооружение раскрывается через туннель и разворачивается в две основные зоны, предлагая захватывающие виды на тирольские долины. Специальное новое здание для размещения инсталляции было спроектировано и в настоящее время строится Obermoser Architects. Тирольский архитектор Иоганн Обермозер и его команда проектируют и реализуют отмеченные наградами коммерческие и жилые здания с 1983 года, включая впечатляющий ресторан Ice Q на вершине Гайслахкогля и станции канатной дороги Gaislachkogelbahn и Giggijochbahn в Зельдене. Сочетая в себе новейшие технологии и суровую современную архитектуру, 007 ELEMENTS создает захватывающий опыт с драматичным кинематографическим звуковым ландшафтом, действие которого происходит на фоне впечатляющих природных пейзажей."
            },
            "UA": {
                "memoir": "007 ELEMENTS – це нова кінематографічна інсталяція про Джеймса Бонда, що відкривається цієї зими на вершині гори Гайслахкогль у Зельдені. Назва 007 ELEMENTS відображає подорож відвідувача серією галерей, кожна з яких втілює майстерність фірмових елементів, що визначають фільм про Джеймса Бонда. Інсталяція буде зосереджена на фільмі «Спектр», знятому в Зельдені, але також представить інші фільми франшизи про Джеймса Бонда. Співпраця між креативним директором проєкту Нілом Каллоу (арт-директором фільмів «Казино «Рояль», «Квант милосердя», «Скайфол» та «Спектр») та керівником дизайну Optimist Inc. Тіно Шедлером та його командою призвела до створення захопливого, інтерактивного та освітнього досвіду, який переносить відвідувачів у світ 007, одночасно розкриваючи, як цей світ влаштований. «Наша мета з 007 ELEMENTS – розповісти історію Бонда емоційно та захопливо», – сказав Каллоу. «Ми хочемо використати це неймовірне місце, щоб перенести наших гостей в середовище Бонда та втілити історії в унікальний та незабутній спосіб». Розташована на висоті 3050 метрів над рівнем моря, будівля площею 1300 квадратних метрів була збудована в горі та має два рівні. Вражаюча споруда, що плавно поєднується з навколишнім середовищем, проявляється через тунель та розгортається на дві основні зони, що пропонують захоплюючі краєвиди на тірольські долини. Нова будівля, розроблена на замовлення для розміщення інсталяції, була спроектована та наразі будується компанією Obermoser Architects. Тірольський архітектор Йоганн Обермозер та його команда планують та реалізують нагороджені комерційні та житлові будівлі з 1983 року, включаючи вражаючий ресторан Ice Q на вершині Гайслахкогля та станції канатних доріг Gaislachkogelbahn та Giggijochbahn у Зельдені. Поєднуючи найсучасніші технології з суворою сучасною архітектурою, 007 ELEMENTS створює захоплюючі враження з драматичним кінематографічним звуковим пейзажем, розташованим посеред вражаючих природних краєвидів."
            },
            "GR": {
                "memoir": "Το 007 ELEMENTS είναι η νέα κινηματογραφική εγκατάσταση του James Bond που εγκαινιάζεται αυτόν τον χειμώνα, χτισμένη στην κορυφή του βουνού Gaislachkogl στο Sölden. Το όνομα 007 ELEMENTS αντικατοπτρίζει το ταξίδι του επισκέπτη μέσα από μια σειρά γκαλερί, καθεμία από τις οποίες συνδυάζει την τέχνη των χαρακτηριστικών στοιχείων που ορίζουν μια ταινία James Bond. Η εγκατάσταση θα επικεντρωθεί στο Spectre, το οποίο γυρίστηκε στο Sölden, αλλά θα περιλαμβάνει και άλλους τίτλους από το franchise του James Bond. Η συνεργασία μεταξύ του δημιουργικού διευθυντή του project, Neal Callow (καλλιτεχνικός διευθυντής στις ταινίες Casino Royale, Quantum Of Solace, Skyfall και Spectre) και του επικεφαλής σχεδιασμού της Optimist Inc., Tino Schaedler, και της ομάδας του, έχει οδηγήσει σε μια καθηλωτική, διαδραστική και εκπαιδευτική εμπειρία που τοποθετεί τους επισκέπτες στον κόσμο του 007, αποκαλύπτοντας παράλληλα πώς είναι φτιαγμένος αυτός ο κόσμος. «Στόχος μας με το 007 ELEMENTS είναι να αφηγηθούμε την αφήγηση της ιστορίας του Bond με έναν συναισθηματικό και συναρπαστικό τρόπο», δήλωσε ο Callow. «Θέλουμε να χρησιμοποιήσουμε αυτήν την απίστευτη τοποθεσία για να τοποθετήσουμε τους επισκέπτες μας στο περιβάλλον του Bond και να ζωντανέψουμε τις ιστορίες με έναν μοναδικό και αξέχαστο τρόπο». Το κτίριο των 1.300 τετραγωνικών μέτρων, που βρίσκεται 3050 μέτρα πάνω από την επιφάνεια της θάλασσας, έχει κατασκευαστεί μέσα στο βουνό και είναι διατεταγμένο σε δύο επίπεδα. Σε άψογη συνύπαρξη με το περιβάλλον του, η εντυπωσιακή κατασκευή αποκαλύπτεται μέσα από μια σήραγγα και ξεδιπλώνεται σε δύο κύριες περιοχές που προσφέρουν εκπληκτική θέα στις κοιλάδες του Τυρόλου. Το νέο, ειδικά κατασκευασμένο κτίριο που θα στεγάσει την εγκατάσταση σχεδιάστηκε και κατασκευάζεται αυτή τη στιγμή από τους Obermoser Architects. Ο Τιρολέζος αρχιτέκτονας Johann Obermoser και η ομάδα του σχεδιάζουν και υλοποιούν βραβευμένα εμπορικά και οικιστικά κτίρια από το 1983, συμπεριλαμβανομένου του εντυπωσιακού εστιατορίου ice Q στην κορυφή του Gaislachkogl και των σταθμών τελεφερίκ Gaislachkogelbahn και Giggijochbahn στο Sölden. Συνδυάζοντας την τεχνολογία αιχμής με την αυστηρή σύγχρονη αρχιτεκτονική, το 007 ELEMENTS δημιουργεί μια συναρπαστική εμπειρία με ένα δραματικό κινηματογραφικό ηχοτοπίο στο μαγευτικό περιβάλλον της φύσης."
            },
            "CY": {
                "memoir": "Το 007 ELEMENTS είναι η νέα κινηματογραφική εγκατάσταση του James Bond που εγκαινιάζεται αυτόν τον χειμώνα, χτισμένη στην κορυφή του βουνού Gaislachkogl στο Sölden. Το όνομα 007 ELEMENTS αντικατοπτρίζει το ταξίδι του επισκέπτη μέσα από μια σειρά γκαλερί, καθεμία από τις οποίες συνδυάζει την τέχνη των χαρακτηριστικών στοιχείων που ορίζουν μια ταινία James Bond. Η εγκατάσταση θα επικεντρωθεί στο Spectre, το οποίο γυρίστηκε στο Sölden, αλλά θα περιλαμβάνει και άλλους τίτλους από το franchise του James Bond. Η συνεργασία μεταξύ του δημιουργικού διευθυντή του project, Neal Callow (καλλιτεχνικός διευθυντής στις ταινίες Casino Royale, Quantum Of Solace, Skyfall και Spectre) και του επικεφαλής σχεδιασμού της Optimist Inc., Tino Schaedler, και της ομάδας του, έχει οδηγήσει σε μια καθηλωτική, διαδραστική και εκπαιδευτική εμπειρία που τοποθετεί τους επισκέπτες στον κόσμο του 007, αποκαλύπτοντας παράλληλα πώς είναι φτιαγμένος αυτός ο κόσμος. «Στόχος μας με το 007 ELEMENTS είναι να αφηγηθούμε την αφήγηση της ιστορίας του Bond με έναν συναισθηματικό και συναρπαστικό τρόπο», δήλωσε ο Callow. «Θέλουμε να χρησιμοποιήσουμε αυτήν την απίστευτη τοποθεσία για να τοποθετήσουμε τους επισκέπτες μας στο περιβάλλον του Bond και να ζωντανέψουμε τις ιστορίες με έναν μοναδικό και αξέχαστο τρόπο». Το κτίριο των 1.300 τετραγωνικών μέτρων, που βρίσκεται 3050 μέτρα πάνω από την επιφάνεια της θάλασσας, έχει κατασκευαστεί μέσα στο βουνό και είναι διατεταγμένο σε δύο επίπεδα. Σε άψογη συνύπαρξη με το περιβάλλον του, η εντυπωσιακή κατασκευή αποκαλύπτεται μέσα από μια σήραγγα και ξεδιπλώνεται σε δύο κύριες περιοχές που προσφέρουν εκπληκτική θέα στις κοιλάδες του Τυρόλου. Το νέο, ειδικά κατασκευασμένο κτίριο που θα στεγάσει την εγκατάσταση σχεδιάστηκε και κατασκευάζεται αυτή τη στιγμή από τους Obermoser Architects. Ο Τιρολέζος αρχιτέκτονας Johann Obermoser και η ομάδα του σχεδιάζουν και υλοποιούν βραβευμένα εμπορικά και οικιστικά κτίρια από το 1983, συμπεριλαμβανομένου του εντυπωσιακού εστιατορίου ice Q στην κορυφή του Gaislachkogl και των σταθμών τελεφερίκ Gaislachkogelbahn και Giggijochbahn στο Sölden. Συνδυάζοντας την τεχνολογία αιχμής με την αυστηρή σύγχρονη αρχιτεκτονική, το 007 ELEMENTS δημιουργεί μια συναρπαστική εμπειρία με ένα δραματικό κινηματογραφικό ηχοτοπίο στο μαγευτικό περιβάλλον της φύσης."
            },
            "TR": {
                "memoir": "007 ELEMENTS, Sölden'deki Gaislachkogl Dağı'nın zirvesine inşa edilen ve bu kış açılışı yapılacak olan yeni James Bond sinematik enstalasyonudur. 007 ELEMENTS adı, ziyaretçilerin her biri bir James Bond filmini tanımlayan imza unsurlarının zanaatını damıtan bir dizi galerideki yolculuğunu yansıtır. Enstalasyon, Sölden'de çekilen Spectre'ye odaklanacak, ancak James Bond serisindeki diğer başlıkları da içerecek. Projenin Yaratıcı Yönetmeni Neal Callow (Casino Royale, Quantum Of Solace, Skyfall ve Spectre'de Sanat Yönetmeni) ve Optimist Inc. Tasarım Başkanı Tino Schaedler ve ekibi arasındaki iş birliği, ziyaretçileri 007 dünyasının içine yerleştirirken bu dünyanın nasıl yapıldığını ortaya koyan sürükleyici, etkileşimli ve eğitici bir deneyimle sonuçlandı. Callow, \"007 ELEMENTS ile amacımız, Bond hikayesinin anlatımını duygusal ve ilgi çekici bir şekilde anlatmak\" dedi. \"Misafirlerimizi Bond'un ortamına yerleştirmek ve hikayeleri benzersiz ve unutulmaz bir şekilde hayata geçirmek için bu inanılmaz konumu kullanmak istiyoruz.\" Deniz seviyesinden 3050 metre yükseklikte bulunan 1.300 metrekarelik bina dağın içine inşa edilmiş ve iki kata yayılmış. Çevresiyle kusursuz bir şekilde bütünleşen etkileyici yapı, bir tünel aracılığıyla kendini gösteriyor ve Tirol vadilerinin muhteşem manzaralarını sunan iki ana alana açılıyor. Tesisi barındıracak özel yapım yeni bina Obermoser Architects tarafından tasarlandı ve şu anda inşa ediliyor. Tirol mimarı Johann Obermoser ve ekibi, 1983'ten beri Gaislachkogl zirvesindeki muhteşem ice Q restoranı ve Sölden'deki Gaislachkogelbahn ve Giggijochbahn teleferik istasyonları da dahil olmak üzere ödüllü ticari ve konut binaları planlıyor ve hayata geçiriyor. Son teknolojiyi sade çağdaş mimariyle birleştiren 007 ELEMENTS, doğanın ilham verici ortamında etkileyici bir sinematik ses manzarasıyla büyüleyici bir deneyim yaratıyor."
            },
            "IT": {
                "memoir": "007 ELEMENTS è la nuova installazione cinematografica di James Bond che aprirà quest'inverno, costruita sulla cima del Gaislachkogl a Sölden. Il nome 007 ELEMENTS riflette il percorso del visitatore attraverso una serie di gallerie, ognuna delle quali distilla l'arte degli elementi distintivi che definiscono un film di James Bond. L'installazione si concentrerà su Spectre, girato a Sölden, ma presenterà anche altri titoli della saga di James Bond. La collaborazione tra il direttore creativo del progetto Neal Callow (direttore artistico di Casino Royale, Quantum of Solace, Skyfall e Spectre) e il responsabile del design di Optimist Inc. Tino Schaedler e il suo team ha dato vita a un'esperienza immersiva, interattiva ed educativa che immerge i visitatori nel mondo di 007, svelandone al contempo la struttura. \"Il nostro obiettivo con 007 ELEMENTS è raccontare la storia di Bond in modo emozionante e coinvolgente\", ha affermato Callow. \"Vogliamo sfruttare questa incredibile location per immergere i nostri ospiti nell'ambiente di Bond e dare vita alle storie in un modo unico e indimenticabile.\" Situato a 3050 metri sul livello del mare, l'edificio di 1.300 metri quadrati è stato costruito all'interno della montagna e si sviluppa su due livelli. In perfetta armonia con l'ambiente circostante, l'imponente struttura si svela attraverso un tunnel e si sviluppa in due aree principali, offrendo viste spettacolari sulle valli tirolesi. Il nuovo edificio su misura che ospiterà l'installazione è stato progettato e attualmente è in costruzione da Obermoser Architects. L'architetto tirolese Johann Obermoser e il suo team progettano e realizzano edifici commerciali e residenziali pluripremiati dal 1983, tra cui lo spettacolare ristorante Ice Q sulla cima del Gaislachkogl e le stazioni delle funivie Gaislachkogelbahn e Giggijochbahn a Sölden. Combinando tecnologie all'avanguardia con un'architettura contemporanea e sobria, 007 ELEMENTS crea un'esperienza avvincente con un suggestivo paesaggio sonoro cinematografico, immerso in un ambiente naturale mozzafiato."
            },
            "FR": {
                "memoir": "007 ELEMENTS est la nouvelle installation cinématographique James Bond inaugurée cet hiver, construite au sommet du Gaislachkogl à Sölden. Le nom 007 ELEMENTS reflète le parcours du visiteur à travers une série de galeries, chacune distillant le savoir-faire des éléments caractéristiques d'un film de James Bond. L'installation se concentrera sur Spectre, tourné à Sölden, mais présentera également d'autres titres de la franchise James Bond. La collaboration entre le directeur artistique du projet, Neal Callow (directeur artistique sur Casino Royale, Quantum Of Solace, Skyfall et Spectre), et Tino Schaedler, responsable du design chez Optimist Inc., et son équipe a donné naissance à une expérience immersive, interactive et éducative qui plonge les visiteurs dans l'univers de 007 tout en révélant sa composition. « Avec 007 ELEMENTS, notre objectif est de raconter l'histoire de James Bond de manière émotionnelle et captivante », a déclaré Callow. « Nous souhaitons profiter de cet emplacement exceptionnel pour plonger nos hôtes dans l'univers de James Bond et donner vie à ses histoires de manière unique et inoubliable. » Situé à 3 050 mètres d'altitude, ce bâtiment de 1 300 mètres carrés a été construit à même la montagne et s'étend sur deux niveaux. S'intégrant harmonieusement à son environnement, l'impressionnante structure se dévoile à travers un tunnel et se déploie en deux espaces principaux offrant des vues spectaculaires sur les vallées tyroliennes. Le nouveau bâtiment sur mesure destiné à accueillir l'installation a été conçu et est actuellement en construction par le cabinet Obermoser Architects. L'architecte tyrolien Johann Obermoser et son équipe conçoivent et réalisent depuis 1983 des bâtiments commerciaux et résidentiels primés, notamment le spectaculaire restaurant Ice Q au sommet du Gaislachkogl et les stations de téléphériques de Gaislachkogelbahn et de Giggijochbahn à Sölden. Combinant une technologie de pointe avec une architecture contemporaine austère, 007 ELEMENTS crée une expérience captivante avec un paysage sonore cinématographique dramatique dans un environnement naturel impressionnant."
            },
            "BE": {
                "memoir": "007 ELEMENTS est la nouvelle installation cinématographique James Bond inaugurée cet hiver, construite au sommet du Gaislachkogl à Sölden. Le nom 007 ELEMENTS reflète le parcours du visiteur à travers une série de galeries, chacune distillant le savoir-faire des éléments caractéristiques d'un film de James Bond. L'installation se concentrera sur Spectre, tourné à Sölden, mais présentera également d'autres titres de la franchise James Bond. La collaboration entre le directeur artistique du projet, Neal Callow (directeur artistique sur Casino Royale, Quantum Of Solace, Skyfall et Spectre), et Tino Schaedler, responsable du design chez Optimist Inc., et son équipe a donné naissance à une expérience immersive, interactive et éducative qui plonge les visiteurs dans l'univers de 007 tout en révélant sa composition. « Avec 007 ELEMENTS, notre objectif est de raconter l'histoire de James Bond de manière émotionnelle et captivante », a déclaré Callow. « Nous souhaitons profiter de cet emplacement exceptionnel pour plonger nos hôtes dans l'univers de James Bond et donner vie à ses histoires de manière unique et inoubliable. » Situé à 3 050 mètres d'altitude, ce bâtiment de 1 300 mètres carrés a été construit à même la montagne et s'étend sur deux niveaux. S'intégrant harmonieusement à son environnement, l'impressionnante structure se dévoile à travers un tunnel et se déploie en deux espaces principaux offrant des vues spectaculaires sur les vallées tyroliennes. Le nouveau bâtiment sur mesure destiné à accueillir l'installation a été conçu et est actuellement en construction par le cabinet Obermoser Architects. L'architecte tyrolien Johann Obermoser et son équipe conçoivent et réalisent depuis 1983 des bâtiments commerciaux et résidentiels primés, notamment le spectaculaire restaurant Ice Q au sommet du Gaislachkogl et les stations de téléphériques de Gaislachkogelbahn et de Giggijochbahn à Sölden. Combinant une technologie de pointe avec une architecture contemporaine austère, 007 ELEMENTS crée une expérience captivante avec un paysage sonore cinématographique dramatique dans un environnement naturel impressionnant."
            },
            "DE": {
                "memoir": "007 ELEMENTS ist die neue James-Bond-Filminstallation, die diesen Winter im Gipfel des Gaislachkogls in Sölden eröffnet wird. Der Name 007 ELEMENTS spiegelt die Reise des Besuchers durch eine Reihe von Galerien wider, die jeweils die handwerklichen Besonderheiten der charakteristischen Elemente eines James-Bond-Films verkörpern. Die Installation konzentriert sich auf „Spectre“, der in Sölden gedreht wurde, zeigt aber auch andere Titel der James-Bond-Reihe. Die Zusammenarbeit zwischen dem Kreativdirektor des Projekts, Neal Callow (Art Director von „Casino Royale“, „Ein Quantum Trost“, „Skyfall“ und „Spectre“), und Tino Schaedler, Designchef von Optimist Inc., und seinem Team hat ein immersives, interaktives und lehrreiches Erlebnis geschaffen, das Besucher in die Welt von 007 eintauchen lässt und gleichzeitig zeigt, wie diese Welt entsteht. „Unser Ziel mit 007 ELEMENTS ist es, die Geschichte von Bond emotional und fesselnd zu erzählen“, so Callow. „Wir möchten diese unglaubliche Location nutzen, um unsere Gäste in Bonds Welt zu versetzen und die Geschichten auf einzigartige und unvergessliche Weise zum Leben zu erwecken.“ Das 1.300 Quadratmeter große Gebäude auf 3.050 Metern Seehöhe wurde in den Berg hineingebaut und erstreckt sich über zwei Ebenen. Nahtlos in die Umgebung integriert, offenbart sich das beeindruckende Bauwerk durch einen Tunnel und entfaltet sich in zwei Hauptbereiche, die einen spektakulären Blick auf die Tiroler Täler bieten. Der maßgeschneiderte Neubau für die Installation wurde von Obermoser Architekten entworfen und wird derzeit errichtet. Der Tiroler Architekt Johann Obermoser und sein Team planen und realisieren seit 1983 preisgekrönte Geschäfts- und Wohngebäude, darunter das spektakuläre Restaurant ice Q auf dem Gipfel des Gaislachkogls sowie die Stationen der Gaislachkogelbahn und der Giggijochbahn in Sölden. Durch die Kombination modernster Technologie mit schlichter, zeitgenössischer Architektur schafft 007 ELEMENTS ein fesselndes Erlebnis mit einer dramatischen, filmischen Klanglandschaft inmitten der beeindruckenden Natur."
            },
            "AT": {
                "memoir": "007 ELEMENTS ist die neue James-Bond-Filminstallation, die diesen Winter im Gipfel des Gaislachkogls in Sölden eröffnet wird. Der Name 007 ELEMENTS spiegelt die Reise des Besuchers durch eine Reihe von Galerien wider, die jeweils die handwerklichen Besonderheiten der charakteristischen Elemente eines James-Bond-Films verkörpern. Die Installation konzentriert sich auf „Spectre“, der in Sölden gedreht wurde, zeigt aber auch andere Titel der James-Bond-Reihe. Die Zusammenarbeit zwischen dem Kreativdirektor des Projekts, Neal Callow (Art Director von „Casino Royale“, „Ein Quantum Trost“, „Skyfall“ und „Spectre“), und Tino Schaedler, Designchef von Optimist Inc., und seinem Team hat ein immersives, interaktives und lehrreiches Erlebnis geschaffen, das Besucher in die Welt von 007 eintauchen lässt und gleichzeitig zeigt, wie diese Welt entsteht. „Unser Ziel mit 007 ELEMENTS ist es, die Geschichte von Bond emotional und fesselnd zu erzählen“, so Callow. „Wir möchten diese unglaubliche Location nutzen, um unsere Gäste in Bonds Welt zu versetzen und die Geschichten auf einzigartige und unvergessliche Weise zum Leben zu erwecken.“ Das 1.300 Quadratmeter große Gebäude auf 3.050 Metern Seehöhe wurde in den Berg hineingebaut und erstreckt sich über zwei Ebenen. Nahtlos in die Umgebung integriert, offenbart sich das beeindruckende Bauwerk durch einen Tunnel und entfaltet sich in zwei Hauptbereiche, die einen spektakulären Blick auf die Tiroler Täler bieten. Der maßgeschneiderte Neubau für die Installation wurde von Obermoser Architekten entworfen und wird derzeit errichtet. Der Tiroler Architekt Johann Obermoser und sein Team planen und realisieren seit 1983 preisgekrönte Geschäfts- und Wohngebäude, darunter das spektakuläre Restaurant ice Q auf dem Gipfel des Gaislachkogls sowie die Stationen der Gaislachkogelbahn und der Giggijochbahn in Sölden. Durch die Kombination modernster Technologie mit schlichter, zeitgenössischer Architektur schafft 007 ELEMENTS ein fesselndes Erlebnis mit einer dramatischen, filmischen Klanglandschaft inmitten der beeindruckenden Natur."
            }
        }
    },
    "European Coffee Culture": {
        "country": "EU", "insignia": "Coffee",
        "maison": "https://coffeeaffection.com/european-coffee-culture",
        "memoir": "While coffee may have started in Ethiopia and quickly spread to the Middle East, hundreds of years later it has found its home in Europe. Needless to say, it has left its indelible mark on the culture of Europe. In comparison to how coffee is consumed in the United States, Europe still knows how to savor it. It’s not a continent that takes kindly to pouring fresh brew into a Styrofoam or paper cup. For Europe, it’s not merely about the product, that is the beverage. It’s about an experience. We will see that it is every bit as much about the coffee house itself as it is about how the coffee is brewed and consumed. Many European coffee cultures, especially those of Western Europe (Spain, Portugal, France) are extremely similar. If we were to go in-depth in describing all of the intricacies of each European country’s coffee culture, you’d be reading for hours. Today we will discuss the big players and influencers. Even though Italian, Spanish, French, Portuguese, and Dutch coffee cultures are all strikingly similar, we would be remiss if we were to forgo discussing the Italian contribution to European coffee culture. What we know as the delicious, milky, frothy, coffee beverages here in the States would be non-existent if it were not for espresso, which is an Italian invention. The original espresso machine patent was filed in 1884 by Angelo Moriondo. The invention of the espresso process was borne out of a desire to solve the problem of slow-brewing coffee. Coffee is extracted faster when ground finer, but the water takes longer to pass through it. How was this resolved? Moriondo realized that steam pressure would push the hot water through the fine grounds and express (hence the name espresso) a standard cup of coffee, but fast. This patent was later put into practice 17 years later. The speed at which this coffee was produced was its main selling point. Fast forward to the 21st century, and now espresso has come to mean a strong, highly concentrated serving of coffee. This is the legacy of Italian coffee.",
        "language": {
            "FR": {
                "title": "La culture des cafés en Europe",
                "memoir": "Si le café est né en Éthiopie et s'est rapidement répandu au Moyen-Orient, des siècles plus tard, il a trouvé refuge en Europe. Il va sans dire qu'il a marqué la culture européenne de son empreinte indélébile. Contrairement à la consommation américaine, l'Europe sait encore le savourer. Ce n'est pas un continent qui apprécie verser une infusion fraîche dans un gobelet en polystyrène ou en carton. Pour l'Europe, l'important n'est pas seulement le produit, mais aussi la boisson. C'est une expérience. Nous verrons qu'il s'agit autant du café lui-même que de la façon dont le café est préparé et consommé. De nombreuses cultures européennes du café, notamment celles d'Europe occidentale (Espagne, Portugal, France), sont extrêmement similaires. Si nous devions décrire en détail toutes les subtilités de la culture du café de chaque pays européen, vous passeriez des heures à lire. Aujourd'hui, nous allons aborder les principaux acteurs et influenceurs. Même si les cultures du café italienne, espagnole, française, portugaise et néerlandaise sont toutes étonnamment similaires, nous aurions tort de passer sous silence la contribution italienne à la culture européenne du café. Ce que nous connaissons comme ces délicieuses boissons au café, laiteuses et mousseuses, ici aux États-Unis, n'existerait pas sans l'espresso, une invention italienne. Le brevet original de la machine à expresso a été déposé en 1884 par Angelo Moriondo. L'invention du procédé expresso est née de la volonté de résoudre le problème de la lenteur de l'infusion du café. Le café est extrait plus rapidement avec une mouture plus fine, mais l'eau met plus de temps à le traverser. Comment a-t-il résolu ce problème ? Moriondo a compris que la pression de la vapeur pousserait l'eau chaude à travers la mouture fine et permettrait d'obtenir (d'où le nom expresso) une tasse de café standard, mais rapidement. Ce brevet a été mis en application 17 ans plus tard. La rapidité de production de ce café était son principal argument de vente. Au XXIe siècle, l'espresso est devenu synonyme de café fort et très concentré. Tel est l'héritage du café italien."
            },
            "BE": {
                "title": "La culture des cafés en Europe",
                "memoir": "Si le café est né en Éthiopie et s'est rapidement répandu au Moyen-Orient, des siècles plus tard, il a trouvé refuge en Europe. Il va sans dire qu'il a marqué la culture européenne de son empreinte indélébile. Contrairement à la consommation américaine, l'Europe sait encore le savourer. Ce n'est pas un continent qui apprécie verser une infusion fraîche dans un gobelet en polystyrène ou en carton. Pour l'Europe, l'important n'est pas seulement le produit, mais aussi la boisson. C'est une expérience. Nous verrons qu'il s'agit autant du café lui-même que de la façon dont le café est préparé et consommé. De nombreuses cultures européennes du café, notamment celles d'Europe occidentale (Espagne, Portugal, France), sont extrêmement similaires. Si nous devions décrire en détail toutes les subtilités de la culture du café de chaque pays européen, vous passeriez des heures à lire. Aujourd'hui, nous allons aborder les principaux acteurs et influenceurs. Même si les cultures du café italienne, espagnole, française, portugaise et néerlandaise sont toutes étonnamment similaires, nous aurions tort de passer sous silence la contribution italienne à la culture européenne du café. Ce que nous connaissons comme ces délicieuses boissons au café, laiteuses et mousseuses, ici aux États-Unis, n'existerait pas sans l'espresso, une invention italienne. Le brevet original de la machine à expresso a été déposé en 1884 par Angelo Moriondo. L'invention du procédé expresso est née de la volonté de résoudre le problème de la lenteur de l'infusion du café. Le café est extrait plus rapidement avec une mouture plus fine, mais l'eau met plus de temps à le traverser. Comment a-t-il résolu ce problème ? Moriondo a compris que la pression de la vapeur pousserait l'eau chaude à travers la mouture fine et permettrait d'obtenir (d'où le nom expresso) une tasse de café standard, mais rapidement. Ce brevet a été mis en application 17 ans plus tard. La rapidité de production de ce café était son principal argument de vente. Au XXIe siècle, l'espresso est devenu synonyme de café fort et très concentré. Tel est l'héritage du café italien."
            },
            "IT": {
                "title": "Cultura del caffè d'Europa",
                "memoir": "Sebbene il caffè sia nato in Etiopia e si sia rapidamente diffuso in Medio Oriente, centinaia di anni dopo ha trovato casa in Europa. Inutile dire che ha lasciato un segno indelebile nella cultura europea. Rispetto al modo in cui il caffè viene consumato negli Stati Uniti, l'Europa sa ancora come assaporarlo. Non è un continente che gradisce versare caffè appena fatto in un bicchiere di polistirolo o di carta. Per l'Europa, non si tratta solo del prodotto, ma della bevanda. Si tratta di un'esperienza. Vedremo che è tanto importante la caffetteria in sé quanto il modo in cui il caffè viene preparato e consumato. Molte culture europee del caffè, soprattutto quelle dell'Europa occidentale (Spagna, Portogallo, Francia), sono estremamente simili. Se dovessimo approfondire la descrizione di tutte le complessità della cultura del caffè di ogni paese europeo, leggereste per ore. Oggi parleremo dei grandi protagonisti e degli influencer. Sebbene le culture del caffè italiana, spagnola, francese, portoghese e olandese siano sorprendentemente simili, saremmo negligenti se rinunciassimo a discutere del contributo italiano alla cultura del caffè europea. Ciò che negli Stati Uniti conosciamo come le deliziose bevande al caffè, lattiginose e schiumose, non esisterebbe se non fosse per l'espresso, che è un'invenzione italiana. Il brevetto originale per la macchina per caffè espresso fu depositato nel 1884 da Angelo Moriondo. L'invenzione del processo espresso nacque dal desiderio di risolvere il problema della lenta estrazione del caffè. Il caffè viene estratto più velocemente quando è macinato più finemente, ma l'acqua impiega più tempo a passarci attraverso. Come si risolse questo problema? Moriondo capì che la pressione del vapore avrebbe spinto l'acqua calda attraverso la polvere fine ed espresso (da cui il nome espresso) una tazza di caffè standard, ma veloce. Questo brevetto fu poi messo in pratica 17 anni dopo. La velocità con cui questo caffè veniva prodotto era il suo principale punto di forza. Facciamo un salto al XXI secolo, e ora l'espresso è diventato sinonimo di una tazza di caffè forte e altamente concentrato. Questa è l'eredità del caffè italiano."
            },
            "RU": {
                "title": "Кафе-культура Европы",
                "memoir": "Хотя кофе, возможно, и появился в Эфиопии и быстро распространился на Ближнем Востоке, сотни лет спустя он нашел свой дом в Европе. Само собой разумеется, что он оставил свой неизгладимый след в культуре Европы. По сравнению с тем, как кофе потребляется в Соединенных Штатах, Европа все еще знает, как его смаковать. Это не тот континент, который с удовольствием наливает свежий напиток в пенопластовый или бумажный стаканчик. Для Европы важен не только продукт, но и напиток. Это опыт. Мы увидим, что дело не только в самой кофейне, но и в том, как кофе варится и потребляется. Многие европейские кофейные культуры, особенно в Западной Европе (Испания, Португалия, Франция), чрезвычайно похожи. Если бы мы углубились в описание всех тонкостей кофейной культуры каждой европейской страны, вы бы читали часами. Сегодня мы обсудим крупных игроков и влиятельных лиц. Несмотря на то, что итальянская, испанская, французская, португальская и голландская кофейные культуры поразительно похожи, было бы упущением с нашей стороны не обсудить итальянский вклад в европейскую кофейную культуру. То, что мы знаем как вкусные, молочные, пенистые кофейные напитки здесь, в Штатах, не существовало бы, если бы не эспрессо, которое является итальянским изобретением. Оригинальный патент на эспрессо-машину был подан в 1884 году Анджело Мориондо. Изобретение процесса эспрессо было вызвано желанием решить проблему медленного заваривания кофе. Кофе экстрагируется быстрее, когда он более тонко помолот, но воде требуется больше времени, чтобы пройти через него. Как это было решено? Мориондо понял, что давление пара протолкнет горячую воду через мелкую гущу и выделит (отсюда и название эспрессо) стандартную чашку кофе, но быстро. Этот патент был позже реализован на практике 17 лет спустя. Скорость, с которой производился этот кофе, была его главным преимуществом. Перенесемся в 21 век, и теперь эспрессо стало означать крепкую, высококонцентрированную порцию кофе. Это наследие итальянского кофе."
            }
        }
    },
    "Gone with the Wind": {
        "country": "US", "insignia": "Pistol",
        "memoir": "Gone with the Wind has been criticized as having perpetuated Civil War myths and black stereotypes. David Reynolds wrote that \"The white women are elegant, their menfolk are noble or at least dashing. And, in the background, the black slaves are mostly dutiful and content, clearly incapable of an independent existence.\" Reynolds likened Gone with the Wind to The Birth of a Nation and other re-imaginings of the South during the era of segregation, in which white Southerners are portrayed as defending traditional values, and the issue of slavery is largely ignored. The film has been described as a \"regression\" that promotes both the myth of the black rapist and the honorable and defensive role of the Ku Klux Klan during Reconstruction, and as a \"social propaganda\" film offering a \"white supremacist\" view of the past.",
        "language": {
            "RU": {
                "title": "Унесённые ветром",
                "memoir": "«Унесенные ветром» критиковались за то, что они увековечивали мифы Гражданской войны и стереотипы о черных. Дэвид Рейнольдс писал, что «белые женщины элегантны, их мужчины благородны или, по крайней мере, лихие. И на заднем плане черные рабы в основном послушны и довольны, явно неспособны к независимому существованию». Рейнольдс сравнил «Унесенные ветром» с «Рождением нации» и другими переосмыслениями Юга в эпоху сегрегации, в которых белые южане изображаются как защитники традиционных ценностей, а проблема рабства в значительной степени игнорируется. Фильм был описан как «регресс», который продвигает как миф о черном насильнике, так и почетную и оборонительную роль Ку-клукс-клана во время Реконструкции, и как фильм «социальной пропаганды», предлагающий «белый супремасистский» взгляд на прошлое."
            }
        }
    },
    "Sabrina Fairchild": {
        "country": "US", "insignia": "Palace",
        "memoir": "Sabrina Fairchild is the young daughter of the Larrabee family's chauffeur, Thomas Fairchild, and has been in love with David Larrabee all her life. David, a three-times-married, non-working playboy, has never paid romantic attention to Sabrina. Since she has lived for years on the Larrabee estate in Long Island New York with her father, to him, she is still a child.",
        "language": {
            "RU": {
                "title": "Сабрина Фэрчайлд",
                "memoir": "Сабрина Фэрчайлд - молодая дочь шофера семьи Ларраби, Томаса Фэрчайлда, и всю жизнь влюблена в Дэвида Ларраби. Дэвид, трижды женатый, неработающий плейбой, никогда не оказывал Сабрине романтического внимания. Поскольку она много лет прожила в поместье Ларраби на Лонг-Айленде, штат Нью-Йорк, со своим отцом, для него она все еще ребенок."
            }
        }
    },
    "Some Like It Hot": {
        "country": "US", "insignia": "OrientExpress",
        "memoir": "In Prohibition-era Chicago, Joe is a jazz saxophone player and an irresponsible, impulsive gambler and ladies' man; Jerry, his anxious friend, is a jazz double bass player. They work in a speakeasy owned by local Mafia boss \"Spats\" Colombo. Tipped off by informant \"Toothpick\" Charlie, the police raid the joint. Joe and Jerry escape, but later accidentally witness Spats and his henchmen gunning down Toothpick and his gang in revenge (an incident inspired by the Saint Valentine's Day Massacre). Spats and his gang see them as they flee. Broke, terrified, and desperate to leave Chicago, Joe and Jerry disguise themselves as women named Josephine and Daphne so they can join Sweet Sue and her Society Syncopators, an all-female band headed by train to Miami. On the train, Joe and Jerry befriend Sugar Kane, the band's vocalist and ukulele player.",
        "language": {
            "RU": {
                "title": "В джазе только девушки",
                "memoir": "В Чикаго эпохи сухого закона Джо - джазовый саксофонист, безответственный, импульсивный игрок и дамский угодник; Джерри, его беспокойный друг, джазовый контрабасист. Они работают в нелегальном баре, принадлежащем местному боссу мафии «Спатсу» Коломбо. Получив наводку от информатора «Зубочистки» Чарли, полиция совершает налет на заведение. Джо и Джерри сбегают, но позже случайно становятся свидетелями того, как Спатс и его приспешники расстреливают Зубочистку и его банду в отместку (инцидент, вдохновленный резней в День святого Валентина). Спатс и его банда видят, как они убегают. Разбитые, напуганные и отчаянно желающие покинуть Чикаго, Джо и Джерри маскируются под женщин по имени Жозефина и Дафна, чтобы присоединиться к Sweet Sue and her Society Syncopators, женской группе, направляющейся поездом в Майами. В поезде Джо и Джерри знакомятся с Шугар Кейн, вокалисткой группы и игроком на укулеле."
            }
        }
    }
}
